{"data":{"attachments":{},"author_id":"1741993395910811648","conversation_id":"1810124116864975185","created_at":"2024-07-09T17:10:00.000Z","edit_controls":{"editable_until":"2024-07-09T18:10:00.000Z","edits_remaining":5,"is_edit_eligible":false},"edit_history_tweet_ids":["1810723088629178690"],"entities":{"mentions":[{"end":12,"id":"1677212807056723974","start":0,"username":"Sanyia_Neko"}]},"geo":{},"id":"1810723088629178690","in_reply_to_user_id":"1677212807056723974","lang":"zh","possibly_sensitive":false,"public_metrics":{"bookmark_count":0,"impression_count":0,"like_count":0,"quote_count":0,"reply_count":0,"retweet_count":0},"referenced_tweets":[{"id":"1810124116864975185","type":"replied_to"}],"reply_settings":"everyone","text":"@Sanyia_Neko 没那么简单的...照这么说诊室都该关门大吉了"},"includes":{"tweets":[{"attachments":{},"author_id":"1741993395910811648","conversation_id":"1810124116864975185","created_at":"2024-07-09T17:10:00.000Z","edit_controls":{"editable_until":"2024-07-09T18:10:00.000Z","edits_remaining":5,"is_edit_eligible":false},"edit_history_tweet_ids":["1810723088629178690"],"entities":{"mentions":[{"end":12,"id":"1677212807056723974","start":0,"username":"Sanyia_Neko"}]},"geo":{},"id":"1810723088629178690","in_reply_to_user_id":"1677212807056723974","lang":"zh","possibly_sensitive":false,"public_metrics":{"bookmark_count":0,"impression_count":0,"like_count":0,"quote_count":0,"reply_count":0,"retweet_count":0},"referenced_tweets":[{"id":"1810124116864975185","type":"replied_to"}],"reply_settings":"everyone","text":"@Sanyia_Neko 没那么简单的...照这么说诊室都该关门大吉了"},{"attachments":{},"author_id":"1677212807056723974","conversation_id":"1810124116864975185","created_at":"2024-07-08T01:29:54.000Z","edit_controls":{"editable_until":"2024-07-08T02:29:54.000Z","edits_remaining":5,"is_edit_eligible":true},"edit_history_tweet_ids":["1810124116864975185"],"entities":{},"geo":{},"id":"1810124116864975185","lang":"zh","possibly_sensitive":false,"public_metrics":{"bookmark_count":13,"impression_count":9431,"like_count":240,"quote_count":1,"reply_count":8,"retweet_count":16},"reply_settings":"everyone","text":"好多人对抑郁症有个奇怪的误解\n“你是不是有什么想不开，你有什么不开心吗，是遭遇什么事情了吗”不是的没有\n想得很开\n想不开的那叫焦虑症\n大部分抑郁症根本没有心情不好\n他心如止水你知道吗\n你打他一巴掌\n他都没有多大波澜你要是想劝\n你就过来抱紧他知道吧\n塞怀里窒息的那种"}],"users":[{"created_at":"2024-01-02T01:22:57.000Z","description":"猫，诗歌，精神动力学。艺术，C#，波粒二象性。回归曲线上的量子生物，无攻击性。","id":"1741993395910811648","location":"0°00′N 260°00′E Mars","name":"炽烈已极","pinned_tweet_id":"1809649123382948242","profile_image_url":"https://pbs.twimg.com/profile_images/1789433740277567488/d3KhwUX1_normal.jpg","protected":false,"public_metrics":{"followers_count":99,"following_count":79,"like_count":1341,"listed_count":0,"tweet_count":554},"username":"AnIncandescence","verified":false},{"created_at":"2023-07-07T07:08:23.000Z","description":"醉后不知天在水,满船清梦压星河","entities":{"url":{"urls":[{"display_url":"sanyia.top","end":23,"expanded_url":"https://www.sanyia.top","start":0,"url":"https://t.co/7plHHdGTaf"}]}},"id":"1677212807056723974","location":"星落湖","name":"雪阳Firmament","pinned_tweet_id":"1810656181402456094","profile_image_url":"https://pbs.twimg.com/profile_images/1810090653738754048/8gL_tl34_normal.jpg","protected":false,"public_metrics":{"followers_count":530,"following_count":374,"like_count":8133,"listed_count":0,"tweet_count":3704},"url":"https://t.co/7plHHdGTaf","username":"Sanyia_Neko","verified":false}]}}