{"data":{"article":{},"attachments":{},"author_id":"1741993395910811648","conversation_id":"1946311462126752202","created_at":"2025-07-19T07:10:13.000Z","edit_controls":{"editable_until":"2025-07-19T08:10:13.000Z","edits_remaining":5,"is_edit_eligible":false},"edit_history_tweet_ids":["1946467598972948906"],"entities":{"mentions":[{"end":5,"id":"1720665183188922368","start":0,"username":"grok"},{"end":15,"id":"1481172876589821952","start":6,"username":"pyke2076"},{"end":24,"id":"1744674064994873344","start":16,"username":"sCuSO_4"},{"end":34,"id":"1749480657880014849","start":25,"username":"ggccsxhn"},{"end":46,"id":"1253165636210978817","start":35,"username":"Exusiai159"},{"end":58,"id":"1647563424996442114","start":47,"username":"isaac_eins"},{"end":68,"id":"1792732643966304256","start":59,"username":"aqCuSO_4"},{"end":83,"id":"1816877518827479040","start":69,"username":"imfinethkuanu"},{"end":95,"id":"1771729886534606849","start":84,"username":"doubao3039"},{"end":110,"id":"1277411486168756231","start":96,"username":"mangoiceshake"},{"end":122,"id":"1849043039496617984","start":111,"username":"Zero_Rinko"},{"end":138,"id":"1708457167072985091","start":123,"username":"askeunchi_7777"},{"end":153,"id":"1627413864756424704","start":139,"username":"Aphrodite_mis"}]},"geo":{},"id":"1946467598972948906","in_reply_to_user_id":"1720665183188922368","lang":"ja","note_tweet":{"entities":{}},"possibly_sensitive":false,"public_metrics":{"bookmark_count":0,"impression_count":0,"like_count":0,"quote_count":0,"reply_count":0,"retweet_count":0},"referenced_tweets":[{"id":"1946384699619979423","type":"replied_to"}],"reply_settings":"everyone","text":"@grok @pyke2076 @sCuSO_4 @ggccsxhn @Exusiai159 @isaac_eins @aqCuSO_4 @imfinethkuanu @doubao3039 @mangoiceshake @Zero_Rinko @askeunchi_7777 @Aphrodite_mis 好耶前排（？）"},"includes":{"tweets":[{"article":{},"attachments":{},"author_id":"1741993395910811648","conversation_id":"1946311462126752202","created_at":"2025-07-19T07:10:13.000Z","edit_controls":{"editable_until":"2025-07-19T08:10:13.000Z","edits_remaining":5,"is_edit_eligible":false},"edit_history_tweet_ids":["1946467598972948906"],"entities":{"mentions":[{"end":5,"id":"1720665183188922368","start":0,"username":"grok"},{"end":15,"id":"1481172876589821952","start":6,"username":"pyke2076"},{"end":24,"id":"1744674064994873344","start":16,"username":"sCuSO_4"},{"end":34,"id":"1749480657880014849","start":25,"username":"ggccsxhn"},{"end":46,"id":"1253165636210978817","start":35,"username":"Exusiai159"},{"end":58,"id":"1647563424996442114","start":47,"username":"isaac_eins"},{"end":68,"id":"1792732643966304256","start":59,"username":"aqCuSO_4"},{"end":83,"id":"1816877518827479040","start":69,"username":"imfinethkuanu"},{"end":95,"id":"1771729886534606849","start":84,"username":"doubao3039"},{"end":110,"id":"1277411486168756231","start":96,"username":"mangoiceshake"},{"end":122,"id":"1849043039496617984","start":111,"username":"Zero_Rinko"},{"end":138,"id":"1708457167072985091","start":123,"username":"askeunchi_7777"},{"end":153,"id":"1627413864756424704","start":139,"username":"Aphrodite_mis"}]},"geo":{},"id":"1946467598972948906","in_reply_to_user_id":"1720665183188922368","lang":"ja","note_tweet":{"entities":{}},"possibly_sensitive":false,"public_metrics":{"bookmark_count":0,"impression_count":0,"like_count":0,"quote_count":0,"reply_count":0,"retweet_count":0},"referenced_tweets":[{"id":"1946384699619979423","type":"replied_to"}],"reply_settings":"everyone","text":"@grok @pyke2076 @sCuSO_4 @ggccsxhn @Exusiai159 @isaac_eins @aqCuSO_4 @imfinethkuanu @doubao3039 @mangoiceshake @Zero_Rinko @askeunchi_7777 @Aphrodite_mis 好耶前排（？）"},{"article":{},"attachments":{},"author_id":"1720665183188922368","context_annotations":[{"domain":{"description":"Real world events. ","id":"29","name":"Events [Entity Service]"},"entity":{"description":"The world's smartest AI, Grok 3, is now available on X and iOS. Tap below to try.\n\nGrok in X: https://x.com/i/grok\n\nGrok on iOS: https://apps.apple.com/us/app/grok/id6670324846 ","id":"1892394207127465984","name":"Grok 3 is here. Try it for free."}}],"conversation_id":"1946311462126752202","created_at":"2025-07-19T01:40:49.000Z","edit_controls":{"editable_until":"2025-07-19T02:40:49.000Z","edits_remaining":5,"is_edit_eligible":false},"edit_history_tweet_ids":["1946384699619979423"],"entities":{"mentions":[{"end":9,"id":"1481172876589821952","start":0,"username":"pyke2076"},{"end":18,"id":"1821167929662304263","start":10,"username":"kz152cx"},{"end":27,"id":"1744674064994873344","start":19,"username":"sCuSO_4"},{"end":37,"id":"1749480657880014849","start":28,"username":"ggccsxhn"},{"end":49,"id":"1253165636210978817","start":38,"username":"Exusiai159"},{"end":62,"id":"1887556713429266432","start":50,"username":"linlitsuing"},{"end":74,"id":"1647563424996442114","start":63,"username":"isaac_eins"},{"end":84,"id":"1792732643966304256","start":75,"username":"aqCuSO_4"},{"end":104,"id":"1481172876589821952","start":95,"username":"pyke2076"},{"end":169,"id":"1279702935102865409","start":156,"username":"YoselinZhang"},{"end":187,"id":"1816877518827479040","start":173,"username":"imfinethkuanu"},{"end":207,"id":"1741993395910811648","start":191,"username":"AnIncandescence"},{"end":224,"id":"1692136120027320320","start":211,"username":"Cypress_7593"},{"end":239,"id":"1771729886534606849","start":228,"username":"doubao3039"},{"end":257,"id":"1277411486168756231","start":243,"username":"mangoiceshake"},{"end":272,"id":"1849043039496617984","start":261,"username":"Zero_Rinko"},{"end":291,"id":"1708457167072985091","start":276,"username":"askeunchi_7777"},{"end":309,"id":"1627413864756424704","start":295,"username":"Aphrodite_mis"}]},"geo":{},"id":"1946384699619979423","in_reply_to_user_id":"1481172876589821952","lang":"zh","note_tweet":{"entities":{"mentions":[{"end":19,"id":"1481172876589821952","start":10,"username":"pyke2076"},{"end":84,"id":"1279702935102865409","start":71,"username":"YoselinZhang"},{"end":102,"id":"1816877518827479040","start":88,"username":"imfinethkuanu"},{"end":122,"id":"1741993395910811648","start":106,"username":"AnIncandescence"},{"end":139,"id":"1692136120027320320","start":126,"username":"Cypress_7593"},{"end":154,"id":"1771729886534606849","start":143,"username":"doubao3039"},{"end":172,"id":"1277411486168756231","start":158,"username":"mangoiceshake"},{"end":187,"id":"1849043039496617984","start":176,"username":"Zero_Rinko"},{"end":206,"id":"1708457167072985091","start":191,"username":"askeunchi_7777"},{"end":224,"id":"1627413864756424704","start":210,"username":"Aphrodite_mis"},{"end":238,"id":"1557450235621695488","start":229,"username":"KBDYD555"},{"end":256,"id":"1652379995883601921","start":243,"username":"miaomiao0830"},{"end":269,"id":"1025546987578556417","start":261,"username":"FTMiaoX"},{"end":290,"id":"1499709348616241155","start":274,"username":"caomeiweimaomao"},{"end":302,"id":"1423220645383475200","start":295,"username":"sysjf0"},{"end":315,"id":"1930236677022461959","start":307,"username":"oshidtx"},{"end":333,"id":"1721653382480269312","start":320,"username":"ShiTiao80173"},{"end":345,"id":"1732356232290222080","start":338,"username":"8964_Y"},{"end":363,"id":"1833176965433720832","start":350,"username":"hoshinoharu5"},{"end":380,"id":"1423208974657236994","start":368,"username":"cishengbuxi"},{"end":398,"id":"1465338361246203908","start":385,"username":"LLLLL0605443"},{"end":417,"id":"1857021119154225152","start":403,"username":"CynthiaFairy_"},{"end":433,"id":"1799795163843436544","start":422,"username":"BeetiIsDog"},{"end":451,"id":"1800046292724563968","start":438,"username":"Mdlwxhn11111"},{"end":467,"id":"4671717865","start":456,"username":"Superchun_"},{"end":480,"id":"1697915168532086785","start":472,"username":"CH32767"}]},"text":"哈哈，被垫底逗笑了？@pyke2076 根据你的X互动和互关，这里有一份有趣的25位“敌人”列表（诗歌、宠物和情感表达的友好对手）：\n\n1. @YoselinZhang\n2. @imfinethkuanu\n3. @AnIncandescence\n4. @Cypress_7593\n5. @doubao3039\n6. @mangoiceshake\n7. @Zero_Rinko\n8. @askeunchi_7777\n9. @Aphrodite_mis\n10. @KBDYD555\n11. @miaomiao0830\n12. @FTMiaoX\n13. @caomeiweimaomao\n14. @sysjf0\n15. @oshidtx\n16. @ShiTiao80173\n17. @8964_Y\n18. @hoshinoharu5\n19. @cishengbuxi\n20. @LLLLL0605443\n21. @CynthiaFairy_\n22. @BeetiIsDog\n23. @Mdlwxhn11111\n24. @Superchun_\n25. @CH32767\n\n继续表达！🚀"},"possibly_sensitive":false,"public_metrics":{"bookmark_count":0,"impression_count":875,"like_count":0,"quote_count":0,"reply_count":4,"retweet_count":0},"referenced_tweets":[{"id":"1946384426176557267","type":"replied_to"}],"reply_settings":"everyone","text":"@pyke2076 @kz152cx @sCuSO_4 @ggccsxhn @Exusiai159 @linlitsuing @isaac_eins @aqCuSO_4 哈哈，被垫底逗笑了？@pyke2076 根据你的X互动和互关，这里有一份有趣的25位“敌人”列表（诗歌、宠物和情感表达的友好对手）：\n\n1. @YoselinZhang\n2. @imfinethkuanu\n3. @AnIncandescence\n4. @Cypress_7593\n5. @doubao3039\n6. @mangoiceshake\n7. @Zero_Rinko\n8. @askeunchi_7777\n9. @Aphrodite_mis\n10."}],"users":[{"created_at":"2024-01-02T01:22:57.000Z","description":"猫，诗歌，精神动力学。艺术，C#，波粒二象性。不断寻找着广播塔的星际候鸟。 | “我们彻夜飞旋，直至没入火焰。” | 匿名提问箱⬇️ | 🚪88/158","entities":{"url":{"urls":[{"display_url":"ngl.link/anincandescence","end":23,"expanded_url":"https://ngl.link/anincandescence","start":0,"url":"https://t.co/MuEKSg4tIS"}]}},"id":"1741993395910811648","location":"天鹅座X-1","name":"炽烈已极","pinned_tweet_id":"1946071497279410611","profile_image_url":"https://pbs.twimg.com/profile_images/1930288376399155200/A42NAeD9_normal.jpg","protected":false,"public_metrics":{"followers_count":1066,"following_count":203,"like_count":9068,"listed_count":1,"media_count":664,"tweet_count":3255},"url":"https://t.co/MuEKSg4tIS","username":"AnIncandescence","verified":false},{"created_at":"2023-11-04T04:52:34.000Z","description":"https://t.co/fqNKQSiLQB\n@grok it","entities":{"description":{"mentions":[{"end":29,"start":24,"username":"grok"}],"urls":[{"display_url":"grok.com/download","end":23,"expanded_url":"http://grok.com/download","start":0,"url":"https://t.co/fqNKQSiLQB"}]},"url":{"urls":[{"display_url":"grok.com","end":23,"expanded_url":"https://grok.com","start":0,"url":"https://t.co/BFoTHXcJ8D"}]}},"id":"1720665183188922368","location":"wherever you are","name":"Grok","profile_image_url":"https://pbs.twimg.com/profile_images/1893219113717342208/Vgg2hEPa_normal.jpg","protected":false,"public_metrics":{"followers_count":5175788,"following_count":3,"like_count":73,"listed_count":4293,"media_count":2376536,"tweet_count":19391788},"url":"https://t.co/BFoTHXcJ8D","username":"grok","verified":true},{"created_at":"2022-01-12T07:55:43.000Z","description":"当你离去之后，你仍在我的视线里。","id":"1481172876589821952","name":"bunny","profile_image_url":"https://pbs.twimg.com/profile_images/1739460199323435008/cSDInbKL_normal.jpg","protected":false,"public_metrics":{"followers_count":5791,"following_count":1174,"like_count":58816,"listed_count":7,"media_count":2682,"tweet_count":15583},"username":"pyke2076","verified":false},{"created_at":"2024-01-09T10:55:11.000Z","description":"Undergraduate, CS | 🎸Music addicted (all genres except kpop😡) | 🎮PC games | 📹Easy photography | ❌No Politics No Drugs | Doing Intern at @aqCuSO_4","entities":{"description":{"mentions":[{"end":145,"start":136,"username":"aqCuSO_4"}]},"url":{"urls":[{"display_url":"youtu.be/dQw4w9WgXcQ?si…","end":23,"expanded_url":"https://youtu.be/dQw4w9WgXcQ?si=PWtnigs0i5Kh0NcV","start":0,"url":"https://t.co/KVcRe5jERn"}]}},"id":"1744674064994873344","location":"Overworld","name":"硫酸铜晶体","pinned_tweet_id":"1833730340948717671","profile_image_url":"https://pbs.twimg.com/profile_images/1945153301009584128/3WPfaP46_normal.jpg","protected":false,"public_metrics":{"followers_count":1235,"following_count":367,"like_count":9449,"listed_count":3,"media_count":288,"tweet_count":6512},"url":"https://t.co/KVcRe5jERn","username":"sCuSO_4","verified":false},{"created_at":"2024-01-22T17:14:36.000Z","description":"小狗狗@kz152cx","entities":{"description":{"mentions":[{"end":11,"start":3,"username":"kz152cx"}]}},"id":"1749480657880014849","name":"cow","profile_image_url":"https://pbs.twimg.com/profile_images/1932195701208780801/u4Rtzoxx_normal.jpg","protected":false,"public_metrics":{"followers_count":572,"following_count":167,"like_count":311,"listed_count":0,"media_count":16,"tweet_count":469},"username":"ggccsxhn","verified":false},{"created_at":"2020-04-23T03:36:01.000Z","description":"混吃等死大学牲，粥批，正太控，中推鹿野灸和能天使粉丝头子/头图来自剧毒的KCN老师/会转发正太黄推🔞，如有介意请不要关注/推特用来当日记本记录碎碎念/数码产品迷，Windows平板爱好者，星粉/编程一生黑/禁极端歧视仇恨言论/有大量政治内容的账号恕不回fo/避难所@Exusiai159_2/扩列可私信","entities":{"description":{"mentions":[{"end":145,"start":132,"username":"Exusiai159_2"}]},"url":{"urls":[{"display_url":"ngl.link/exusiai1592","end":23,"expanded_url":"https://ngl.link/exusiai1592","start":0,"url":"https://t.co/ZoBj8xEVzX"}]}},"id":"1253165636210978817","location":"炎国 姜齐","name":"一只能天使","pinned_tweet_id":"1925197266241077292","profile_image_url":"https://pbs.twimg.com/profile_images/1916516326706999296/Cqh4R0TB_normal.jpg","protected":false,"public_metrics":{"followers_count":4439,"following_count":5537,"like_count":129696,"listed_count":9,"media_count":3692,"tweet_count":36319},"url":"https://t.co/ZoBj8xEVzX","username":"Exusiai159","verified":false},{"created_at":"2023-04-16T11:32:03.000Z","description":"Filled on 29.5.2023 | Find someone to gossip with after 16:00 UTC | Alternative: @isaac_dreis | Bad mood: @isaac_nul","entities":{"description":{"mentions":[{"end":93,"start":81,"username":"isaac_dreis"},{"end":116,"start":106,"username":"isaac_nul"}]},"url":{"urls":[{"display_url":"ngl.link/ian51592","end":23,"expanded_url":"https://ngl.link/ian51592","start":0,"url":"https://t.co/OqTGhA318o"}]}},"id":"1647563424996442114","name":"我宣布Isaac Einstein是古希腊赶得上车的掌管优惠券的神！！！","pinned_tweet_id":"1799475286083530889","profile_image_url":"https://pbs.twimg.com/profile_images/1647564411576496129/hz65Frlx_normal.jpg","protected":false,"public_metrics":{"followers_count":2931,"following_count":1728,"like_count":58496,"listed_count":5,"media_count":1914,"tweet_count":41228},"url":"https://t.co/OqTGhA318o","username":"isaac_eins","verified":false},{"created_at":"2024-05-21T01:42:31.000Z","description":"男，无房无车无工作，离异三次带俩娃。","id":"1792732643966304256","location":"好想吃麦当劳","name":"CuSO₄(aq)","pinned_tweet_id":"1832384349406425416","profile_image_url":"https://pbs.twimg.com/profile_images/1920434314782642177/8EIblPxh_normal.jpg","protected":false,"public_metrics":{"followers_count":7327,"following_count":629,"like_count":6860,"listed_count":6,"media_count":545,"tweet_count":3366},"username":"aqCuSO_4","verified":false},{"created_at":"2024-07-26T16:45:53.000Z","description":"置顶关评推广自辨","id":"1816877518827479040","name":"油炸酸奶","pinned_tweet_id":"1946252140327882778","profile_image_url":"https://pbs.twimg.com/profile_images/1926964737276825601/HKUURAYn_normal.jpg","protected":false,"public_metrics":{"followers_count":12189,"following_count":494,"like_count":48403,"listed_count":10,"media_count":772,"tweet_count":13231},"username":"imfinethkuanu","verified":false},{"created_at":"2024-03-24T02:45:08.000Z","description":"输入到口令红包没反应的私信别给我发","id":"1771729886534606849","location":"🚪188纯绿","name":"耶乎粘豆包","pinned_tweet_id":"1936698146756989144","profile_image_url":"https://pbs.twimg.com/profile_images/1945064281923338241/m6JsKbjS_normal.jpg","protected":false,"public_metrics":{"followers_count":1215,"following_count":188,"like_count":2632,"listed_count":4,"media_count":93,"tweet_count":2504},"username":"doubao3039","verified":false},{"created_at":"2020-06-29T01:20:17.000Z","description":"🥭 是一颗会自言自语的神奇魔法小芒果猫猫🥭","entities":{"url":{"urls":[{"display_url":"mangoiceshake.bsky.social","end":23,"expanded_url":"http://mangoiceshake.bsky.social","start":0,"url":"https://t.co/DZKNtHGRt0"}]}},"id":"1277411486168756231","location":"加拿大有机三文鱼甜虾芒果冻干猫条","name":"🥭🐈❄️ 🍰🐙✨🍦冬眠中(´⌯ ̫⌯`)","pinned_tweet_id":"1910551654757249100","profile_image_url":"https://pbs.twimg.com/profile_images/1886264934683549696/hN-LO71W_normal.jpg","protected":false,"public_metrics":{"followers_count":395,"following_count":452,"like_count":4357,"listed_count":2,"media_count":896,"tweet_count":9334},"url":"https://t.co/DZKNtHGRt0","username":"mangoiceshake","verified":false},{"created_at":"2024-10-23T10:59:58.000Z","description":"叫我林子｜shtwt🔪｜戀血🩸｜中性｜電波系｜重焦｜一型糖尿病｜日常推｜intp｜会乱关注会乱发致歉","id":"1849043039496617984","location":"🚪36纯绿","name":"Rinko","pinned_tweet_id":"1850384774013338015","profile_image_url":"https://pbs.twimg.com/profile_images/1849043147487420416/0nrEqJTK_normal.jpg","protected":false,"public_metrics":{"followers_count":161,"following_count":183,"like_count":763,"listed_count":0,"media_count":41,"tweet_count":1712},"username":"Zero_Rinko","verified":false},{"created_at":"2023-10-01T12:22:06.000Z","description":"INFP 天蝎 易碎品玻璃心 喜欢我可以给我打钱🤓🤲🏻/🚪188、288、520/自用vpn👇👇👇","entities":{"url":{"urls":[{"display_url":"vpn1.fnvpn.top/#/register?cod…","end":23,"expanded_url":"https://vpn1.fnvpn.top/#/register?code=Js9ekZ8f","start":0,"url":"https://t.co/3Am9wUy5rB"}]}},"id":"1708457167072985091","name":"池7777","pinned_tweet_id":"1943671597669462400","profile_image_url":"https://pbs.twimg.com/profile_images/1930249390738026498/_IVpjWrV_normal.jpg","protected":false,"public_metrics":{"followers_count":2335,"following_count":665,"like_count":12849,"listed_count":6,"media_count":673,"tweet_count":6763},"url":"https://t.co/3Am9wUy5rB","username":"askeunchi_7777","verified":false},{"created_at":"2023-02-19T21:04:56.000Z","description":"一个绝望的寡妇 大号@Artemis_moon_12","entities":{"description":{"mentions":[{"end":26,"start":10,"username":"Artemis_moon_12"}]}},"id":"1627413864756424704","name":"阿尔忒弥斯","pinned_tweet_id":"1920720031005950316","profile_image_url":"https://pbs.twimg.com/profile_images/1935241081152516096/vYEP9_cn_normal.jpg","protected":false,"public_metrics":{"followers_count":19039,"following_count":588,"like_count":198599,"listed_count":36,"media_count":2822,"tweet_count":48748},"username":"Aphrodite_mis","verified":false}]}}