{"data":{"article":{},"attachments":{},"author_id":"1741993395910811648","conversation_id":"1947213143270420794","created_at":"2025-07-23T06:36:56.000Z","edit_controls":{"editable_until":"2025-07-23T07:36:56.000Z","edits_remaining":5,"is_edit_eligible":false},"edit_history_tweet_ids":["1947908772246286529"],"entities":{"mentions":[{"end":11,"id":"1849043039496617984","start":0,"username":"Zero_Rinko"}]},"geo":{},"id":"1947908772246286529","in_reply_to_user_id":"1849043039496617984","lang":"zh","note_tweet":{"entities":{}},"possibly_sensitive":false,"public_metrics":{"bookmark_count":0,"impression_count":0,"like_count":0,"quote_count":0,"reply_count":0,"retweet_count":0},"referenced_tweets":[{"id":"1947806418394091900","type":"replied_to"}],"reply_settings":"everyone","text":"@Zero_Rinko 我这边看也是的，诊断上写几乎都是抑郁状态/抑郁发作之类的而非抑郁症，最早听到的原因版本是为了避免影响投保（？）实际上应该是满足诊断标准的...后来在住院的时候病历上写的就成重度了x"},"includes":{"tweets":[{"article":{},"attachments":{},"author_id":"1741993395910811648","conversation_id":"1947213143270420794","created_at":"2025-07-23T06:36:56.000Z","edit_controls":{"editable_until":"2025-07-23T07:36:56.000Z","edits_remaining":5,"is_edit_eligible":false},"edit_history_tweet_ids":["1947908772246286529"],"entities":{"mentions":[{"end":11,"id":"1849043039496617984","start":0,"username":"Zero_Rinko"}]},"geo":{},"id":"1947908772246286529","in_reply_to_user_id":"1849043039496617984","lang":"zh","note_tweet":{"entities":{}},"possibly_sensitive":false,"public_metrics":{"bookmark_count":0,"impression_count":0,"like_count":0,"quote_count":0,"reply_count":0,"retweet_count":0},"referenced_tweets":[{"id":"1947806418394091900","type":"replied_to"}],"reply_settings":"everyone","text":"@Zero_Rinko 我这边看也是的，诊断上写几乎都是抑郁状态/抑郁发作之类的而非抑郁症，最早听到的原因版本是为了避免影响投保（？）实际上应该是满足诊断标准的...后来在住院的时候病历上写的就成重度了x"},{"article":{},"attachments":{},"author_id":"1849043039496617984","conversation_id":"1947213143270420794","created_at":"2025-07-22T23:50:13.000Z","edit_controls":{"editable_until":"2025-07-23T00:50:13.000Z","edits_remaining":5,"is_edit_eligible":false},"edit_history_tweet_ids":["1947806418394091900"],"entities":{"mentions":[{"end":16,"id":"1741993395910811648","start":0,"username":"AnIncandescence"}]},"geo":{},"id":"1947806418394091900","in_reply_to_user_id":"1741993395910811648","lang":"zh","note_tweet":{"entities":{}},"possibly_sensitive":false,"public_metrics":{"bookmark_count":0,"impression_count":33,"like_count":2,"quote_count":0,"reply_count":0,"retweet_count":1},"referenced_tweets":[{"id":"1947213143270420794","type":"replied_to"}],"reply_settings":"everyone","text":"@AnIncandescence 我想知道自己怎么了，我想知道关于我自己的一切，但是我不知道从何下手，具体应该怎么做呢我去医院检查医生只会给我简单的开个抑郁焦虑量表做完也不会确诊之类只告诉我抑郁焦虑状态然后让我吃点药但是药物对我的作用微乎其微"}],"users":[{"created_at":"2024-01-02T01:22:57.000Z","description":"猫，诗歌，精神动力学。艺术，朝闻道，波粒二象性。不断寻找着广播塔的星际候鸟。 | “我们彻夜飞旋，直至没入火焰。” | 匿名提问箱⬇️ | 🚪88/158","entities":{"url":{"urls":[{"display_url":"ngl.link/anincandescence","end":23,"expanded_url":"https://ngl.link/anincandescence","start":0,"url":"https://t.co/MuEKSg4tIS"}]}},"id":"1741993395910811648","location":"天鹅座X-1","name":"炽烈已极","pinned_tweet_id":"1944465960406245490","profile_image_url":"https://pbs.twimg.com/profile_images/1947176726292725760/VAZ0WSeY_normal.jpg","protected":false,"public_metrics":{"followers_count":1094,"following_count":205,"like_count":9239,"listed_count":1,"media_count":673,"tweet_count":3324},"url":"https://t.co/MuEKSg4tIS","username":"AnIncandescence","verified":false},{"created_at":"2024-10-23T10:59:58.000Z","description":"叫我林子｜shtwt🔪｜戀血🩸｜中性｜電波系｜重焦｜一糖｜会乱关注会乱发致歉","id":"1849043039496617984","location":"🚪36纯绿","name":"Rinko","pinned_tweet_id":"1850384774013338015","profile_image_url":"https://pbs.twimg.com/profile_images/1849043147487420416/0nrEqJTK_normal.jpg","protected":false,"public_metrics":{"followers_count":181,"following_count":195,"like_count":809,"listed_count":0,"media_count":43,"tweet_count":1850},"username":"Zero_Rinko","verified":false}]}}