{"data":{"article":{},"attachments":{},"author_id":"1741993395910811648","conversation_id":"1901175700490703349","created_at":"2025-03-16T07:36:23.000Z","edit_controls":{"editable_until":"2025-03-16T08:36:23.000Z","edits_remaining":5,"is_edit_eligible":true},"edit_history_tweet_ids":["1901175700490703349"],"entities":{"mentions":[{"end":24,"id":"1705582301642653696","start":13,"username":"miuchisama"},{"end":42,"id":"1595415869689044992","start":26,"username":"xiaobai04712114"},{"end":54,"id":"1347140950095613953","start":44,"username":"nejamais1"}],"urls":[{"display_url":"x.com/anincandescenc…","end":78,"expanded_url":"https://twitter.com/anincandescence/status/1896010753083392328","start":55,"url":"https://t.co/XCYnTtv34F"}]},"geo":{},"id":"1901175700490703349","lang":"zh","note_tweet":{"entities":{}},"possibly_sensitive":false,"public_metrics":{"bookmark_count":0,"impression_count":0,"like_count":0,"quote_count":0,"reply_count":0,"retweet_count":0},"referenced_tweets":[{"id":"1896010753083392328","type":"quoted"}],"reply_settings":"everyone","text":"开随机数！请中奖私信我～\n@miuchisama \n@xiaobai04712114 \n@nejamais1 https://t.co/XCYnTtv34F"},"includes":{"tweets":[{"article":{},"attachments":{},"author_id":"1741993395910811648","conversation_id":"1901175700490703349","created_at":"2025-03-16T07:36:23.000Z","edit_controls":{"editable_until":"2025-03-16T08:36:23.000Z","edits_remaining":5,"is_edit_eligible":true},"edit_history_tweet_ids":["1901175700490703349"],"entities":{"mentions":[{"end":24,"id":"1705582301642653696","start":13,"username":"miuchisama"},{"end":42,"id":"1595415869689044992","start":26,"username":"xiaobai04712114"},{"end":54,"id":"1347140950095613953","start":44,"username":"nejamais1"}],"urls":[{"display_url":"x.com/anincandescenc…","end":78,"expanded_url":"https://twitter.com/anincandescence/status/1896010753083392328","start":55,"url":"https://t.co/XCYnTtv34F"}]},"geo":{},"id":"1901175700490703349","lang":"zh","note_tweet":{"entities":{}},"possibly_sensitive":false,"public_metrics":{"bookmark_count":0,"impression_count":0,"like_count":0,"quote_count":0,"reply_count":0,"retweet_count":0},"referenced_tweets":[{"id":"1896010753083392328","type":"quoted"}],"reply_settings":"everyone","text":"开随机数！请中奖私信我～\n@miuchisama \n@xiaobai04712114 \n@nejamais1 https://t.co/XCYnTtv34F"},{"article":{},"attachments":{},"author_id":"1741993395910811648","conversation_id":"1896010753083392328","created_at":"2025-03-02T01:32:44.000Z","edit_controls":{"editable_until":"2025-03-02T02:32:44.000Z","edits_remaining":5,"is_edit_eligible":false},"edit_history_tweet_ids":["1896010753083392328"],"entities":{"urls":[{"display_url":"x.com/anincandescenc…","end":96,"expanded_url":"https://twitter.com/anincandescence/status/1896009323920404722","start":73,"url":"https://t.co/jXax2ZGnWW"}]},"geo":{},"id":"1896010753083392328","lang":"zh","note_tweet":{"entities":{}},"possibly_sensitive":false,"public_metrics":{"bookmark_count":1,"impression_count":2128,"like_count":10,"quote_count":2,"reply_count":7,"retweet_count":1},"referenced_tweets":[{"id":"1896009323920404722","type":"quoted"}],"reply_settings":"everyone","text":"快300fo啦🎉开心\n\n转评赞置顶贴揪3位送小礼物\n掉落个人手作/robo dxm美版散装/30🧧可选\n\n欢迎互动✧٩(ˊωˋ*)و✧此处可点歌 https://t.co/jXax2ZGnWW"}],"users":[{"created_at":"2024-01-02T01:22:57.000Z","description":"互fo欢迎！ 猫，诗歌，精神动力学。艺术，C#，波粒二象性。回归曲线上的量子生物，无攻击性。“我们彻夜飞旋，直至没入火焰。”阴暗碎碎念纯享版@TauCeti_10700 提问箱👇","entities":{"description":{"mentions":[{"end":84,"start":70,"username":"TauCeti_10700"}]},"url":{"urls":[{"display_url":"ngl.link/anincandescence","end":23,"expanded_url":"https://ngl.link/anincandescence","start":0,"url":"https://t.co/MuEKSg4tIS"}]}},"id":"1741993395910811648","location":"0°00′N 260°00′E Mars","name":"炽烈已极","pinned_tweet_id":"1896009323920404722","profile_image_url":"https://pbs.twimg.com/profile_images/1789433740277567488/d3KhwUX1_normal.jpg","protected":false,"public_metrics":{"followers_count":324,"following_count":167,"like_count":5021,"listed_count":1,"media_count":411,"tweet_count":1736},"url":"https://t.co/MuEKSg4tIS","username":"AnIncandescence","verified":false},{"created_at":"2023-09-23T13:58:13.000Z","description":"꒰ঌ૮₍ • ˕ - ₎ა໒꒱🩷₊˚","id":"1705582301642653696","location":"消失了","name":"美内🌸","pinned_tweet_id":"1869054520137052558","profile_image_url":"https://pbs.twimg.com/profile_images/1892982577772011523/p7GxbOV__normal.jpg","protected":false,"public_metrics":{"followers_count":2060,"following_count":472,"like_count":13080,"listed_count":4,"media_count":64,"tweet_count":1162},"username":"miuchisama","verified":false},{"created_at":"2022-11-23T13:56:16.000Z","description":"诶嘿","id":"1595415869689044992","name":"xiaobai","profile_image_url":"https://pbs.twimg.com/profile_images/1827051727801217025/qswLxp_q_normal.jpg","protected":false,"public_metrics":{"followers_count":15,"following_count":24,"like_count":18,"listed_count":0,"media_count":0,"tweet_count":20},"username":"xiaobai04712114","verified":false},{"created_at":"2021-01-07T11:22:13.000Z","description":"男的/可以叫我小天","id":"1347140950095613953","name":"Polarstern","pinned_tweet_id":"1895562422930587880","profile_image_url":"https://pbs.twimg.com/profile_images/1896590731726528512/1xlvoAx9_normal.jpg","protected":false,"public_metrics":{"followers_count":136,"following_count":370,"like_count":3335,"listed_count":1,"media_count":156,"tweet_count":3147},"username":"nejamais1","verified":false}]}}