{"data":{"article":{},"attachments":{},"author_id":"1741993395910811648","conversation_id":"1896043452133171652","created_at":"2025-03-29T12:16:49.000Z","edit_controls":{"editable_until":"2025-03-29T13:16:49.000Z","edits_remaining":5,"is_edit_eligible":false},"edit_history_tweet_ids":["1905957315746107809"],"entities":{"mentions":[{"end":12,"id":"1763381254035251200","start":0,"username":"Naii3120720"}]},"geo":{},"id":"1905957315746107809","in_reply_to_user_id":"1763381254035251200","lang":"zh","note_tweet":{"entities":{}},"possibly_sensitive":false,"public_metrics":{"bookmark_count":0,"impression_count":0,"like_count":0,"quote_count":0,"reply_count":0,"retweet_count":0},"referenced_tweets":[{"id":"1905956640853225738","type":"replied_to"}],"reply_settings":"everyone","text":"@Naii3120720 宝宝(๑˘³˘๑)💗你非常好非常棒\n坚持自己珍贵的本心吧"},"includes":{"tweets":[{"article":{},"attachments":{},"author_id":"1741993395910811648","conversation_id":"1896043452133171652","created_at":"2025-03-29T12:16:49.000Z","edit_controls":{"editable_until":"2025-03-29T13:16:49.000Z","edits_remaining":5,"is_edit_eligible":false},"edit_history_tweet_ids":["1905957315746107809"],"entities":{"mentions":[{"end":12,"id":"1763381254035251200","start":0,"username":"Naii3120720"}]},"geo":{},"id":"1905957315746107809","in_reply_to_user_id":"1763381254035251200","lang":"zh","note_tweet":{"entities":{}},"possibly_sensitive":false,"public_metrics":{"bookmark_count":0,"impression_count":0,"like_count":0,"quote_count":0,"reply_count":0,"retweet_count":0},"referenced_tweets":[{"id":"1905956640853225738","type":"replied_to"}],"reply_settings":"everyone","text":"@Naii3120720 宝宝(๑˘³˘๑)💗你非常好非常棒\n坚持自己珍贵的本心吧"},{"article":{},"attachments":{},"author_id":"1763381254035251200","conversation_id":"1896043452133171652","created_at":"2025-03-29T12:14:08.000Z","edit_controls":{"editable_until":"2025-03-29T13:14:08.000Z","edits_remaining":5,"is_edit_eligible":false},"edit_history_tweet_ids":["1905956640853225738"],"entities":{"mentions":[{"end":16,"id":"1741993395910811648","start":0,"username":"AnIncandescence"}]},"geo":{},"id":"1905956640853225738","in_reply_to_user_id":"1741993395910811648","lang":"zh","note_tweet":{"entities":{}},"possibly_sensitive":false,"public_metrics":{"bookmark_count":0,"impression_count":3,"like_count":1,"quote_count":0,"reply_count":1,"retweet_count":0},"referenced_tweets":[{"id":"1905955533632462930","type":"replied_to"}],"reply_settings":"everyone","text":"@AnIncandescence 😌谢谢，感受到了鼓舞，尸体回温了……天天开心！"}],"users":[{"created_at":"2024-01-02T01:22:57.000Z","description":"互fo欢迎！ 猫，诗歌，精神动力学。艺术，C#，波粒二象性。回归曲线上的量子生物，无攻击性。 | “我们彻夜飞旋，直至没入火焰。” | 阴暗碎碎念纯享版@TauCeti_10700 | 🚪88/158 |  提问箱👇","entities":{"description":{"mentions":[{"end":90,"start":76,"username":"TauCeti_10700"}]},"url":{"urls":[{"display_url":"ngl.link/anincandescence","end":23,"expanded_url":"https://ngl.link/anincandescence","start":0,"url":"https://t.co/MuEKSg3VTk"}]}},"id":"1741993395910811648","location":"0°00′N 260°00′E Mars","name":"炽烈已极","pinned_tweet_id":"1905895186867400960","profile_image_url":"https://pbs.twimg.com/profile_images/1789433740277567488/d3KhwUX1_normal.jpg","protected":false,"public_metrics":{"followers_count":423,"following_count":181,"like_count":5526,"listed_count":1,"media_count":457,"tweet_count":1998},"url":"https://t.co/MuEKSg3VTk","username":"AnIncandescence","verified":false},{"created_at":"2024-03-01T01:50:39.000Z","description":"我好想！成为人类啊！ 奋斗百年，我是禁毒宣传大使🤓️","id":"1763381254035251200","location":"掌声存在之地","name":"弱虫モンブラン","pinned_tweet_id":"1784505372524638218","profile_image_url":"https://pbs.twimg.com/profile_images/1779196974153261056/sAf9Rk_6_normal.jpg","protected":false,"public_metrics":{"followers_count":138,"following_count":275,"like_count":19865,"listed_count":1,"media_count":99,"tweet_count":1967},"username":"Naii3120720","verified":false}]}}