{"data":{"article":{},"attachments":{},"author_id":"1741993395910811648","conversation_id":"1989245996761772053","created_at":"2025-11-14T08:44:03.000Z","edit_controls":{"editable_until":"2025-11-14T09:44:03.000Z","edits_remaining":5,"is_edit_eligible":false},"edit_history_tweet_ids":["1989252979128738196"],"entities":{"mentions":[{"end":9,"id":"1494669485214633984","start":0,"username":"57crz3oA"}]},"geo":{},"id":"1989252979128738196","in_reply_to_user_id":"1494669485214633984","lang":"zh","note_tweet":{"entities":{}},"possibly_sensitive":false,"public_metrics":{"bookmark_count":0,"impression_count":0,"like_count":0,"quote_count":0,"reply_count":0,"retweet_count":0},"referenced_tweets":[{"id":"1989251569444147686","type":"replied_to"}],"reply_settings":"everyone","text":"@57crz3oA 直视的时候眼睛会刺痛有时也忍不住去看，我记得那半片被点燃的天空。\n会有些失落的时分却不知为何，明明白天和夜晚都算不上喜欢。据说也被称作逢魔之时，或许能看到一些不存在于这一侧世界的事物吗？"},"includes":{"tweets":[{"article":{},"attachments":{},"author_id":"1741993395910811648","conversation_id":"1989245996761772053","created_at":"2025-11-14T08:44:03.000Z","edit_controls":{"editable_until":"2025-11-14T09:44:03.000Z","edits_remaining":5,"is_edit_eligible":false},"edit_history_tweet_ids":["1989252979128738196"],"entities":{"mentions":[{"end":9,"id":"1494669485214633984","start":0,"username":"57crz3oA"}]},"geo":{},"id":"1989252979128738196","in_reply_to_user_id":"1494669485214633984","lang":"zh","note_tweet":{"entities":{}},"possibly_sensitive":false,"public_metrics":{"bookmark_count":0,"impression_count":0,"like_count":0,"quote_count":0,"reply_count":0,"retweet_count":0},"referenced_tweets":[{"id":"1989251569444147686","type":"replied_to"}],"reply_settings":"everyone","text":"@57crz3oA 直视的时候眼睛会刺痛有时也忍不住去看，我记得那半片被点燃的天空。\n会有些失落的时分却不知为何，明明白天和夜晚都算不上喜欢。据说也被称作逢魔之时，或许能看到一些不存在于这一侧世界的事物吗？"},{"article":{},"attachments":{},"author_id":"1494669485214633984","conversation_id":"1989245996761772053","created_at":"2025-11-14T08:38:27.000Z","edit_controls":{"editable_until":"2025-11-14T09:38:27.000Z","edits_remaining":5,"is_edit_eligible":false},"edit_history_tweet_ids":["1989251569444147686"],"entities":{"mentions":[{"end":16,"id":"1741993395910811648","start":0,"username":"AnIncandescence"}]},"geo":{},"id":"1989251569444147686","in_reply_to_user_id":"1741993395910811648","lang":"ja","note_tweet":{"entities":{}},"possibly_sensitive":false,"public_metrics":{"bookmark_count":0,"impression_count":4,"like_count":1,"quote_count":0,"reply_count":1,"retweet_count":0},"referenced_tweets":[{"id":"1989245996761772053","type":"replied_to"}],"reply_settings":"everyone","text":"@AnIncandescence 日落"}],"users":[{"created_at":"2024-01-02T01:22:57.000Z","description":"猫，诗歌，精神动力学。艺术，朝闻道，波粒二象性。不断寻找着广播塔的星际候鸟。 | “我们彻夜飞旋，直至没入火焰。” | 匿名提问箱⬇️ | 🚪88/158","entities":{"url":{"urls":[{"display_url":"ngl.link/anincandescenc…","end":23,"expanded_url":"https://ngl.link/anincandescence1","start":0,"url":"https://t.co/iO6MRJNm9j"}]}},"id":"1741993395910811648","location":"天鹅座X-1","name":"炽烈已极","pinned_tweet_id":"1976277813784457417","profile_image_url":"https://pbs.twimg.com/profile_images/1967287311504465922/Z7d-hW5p_normal.jpg","protected":false,"public_metrics":{"followers_count":1274,"following_count":213,"like_count":11276,"listed_count":3,"media_count":844,"tweet_count":4338},"url":"https://t.co/iO6MRJNm9j","username":"AnIncandescence","verified":false},{"created_at":"2022-02-18T13:45:58.000Z","description":"ad astra per aspera","entities":{"url":{"urls":[{"display_url":"ngl.link/stcr2304","end":23,"expanded_url":"https://ngl.link/stcr2304","start":0,"url":"https://t.co/u1lxDXQeX0"}]}},"id":"1494669485214633984","name":"s2R2304","pinned_tweet_id":"1931931078182547903","profile_image_url":"https://pbs.twimg.com/profile_images/1935336561887076352/EYsfHVDn_normal.jpg","protected":false,"public_metrics":{"followers_count":347,"following_count":1121,"like_count":53495,"listed_count":3,"media_count":253,"tweet_count":2706},"url":"https://t.co/u1lxDXQeX0","username":"57crz3oA","verified":false}]}}