{"data":{"article":{},"attachments":{"media_keys":["3_1982225220598464512"]},"author_id":"1741993395910811648","conversation_id":"1982225228789960905","created_at":"2025-10-25T23:18:17.000Z","edit_controls":{"editable_until":"2025-10-26T00:18:17.000Z","edits_remaining":5,"is_edit_eligible":true},"edit_history_tweet_ids":["1982225228789960905"],"entities":{"urls":[{"display_url":"pic.x.com/lrN2d4vauD","end":35,"expanded_url":"https://x.com/AnIncandescence/status/1982225228789960905/photo/1","media_key":"3_1982225220598464512","start":12,"url":"https://t.co/lrN2d4vauD"}]},"geo":{},"id":"1982225228789960905","lang":"zh","note_tweet":{"entities":{}},"possibly_sensitive":false,"public_metrics":{"bookmark_count":0,"impression_count":0,"like_count":0,"quote_count":0,"reply_count":0,"retweet_count":0},"reply_settings":"everyone","text":"连阴影都如思绪般杂乱. https://t.co/lrN2d4vauD"},"includes":{"media":[{"height":4032,"media_key":"3_1982225220598464512","public_metrics":{},"type":"photo","url":"https://pbs.twimg.com/media/G4JHVfqXgAAQSPp.jpg","width":3024}],"tweets":[{"article":{},"attachments":{"media_keys":["3_1982225220598464512"]},"author_id":"1741993395910811648","conversation_id":"1982225228789960905","created_at":"2025-10-25T23:18:17.000Z","edit_controls":{"editable_until":"2025-10-26T00:18:17.000Z","edits_remaining":5,"is_edit_eligible":true},"edit_history_tweet_ids":["1982225228789960905"],"entities":{"urls":[{"display_url":"pic.x.com/lrN2d4vauD","end":35,"expanded_url":"https://x.com/AnIncandescence/status/1982225228789960905/photo/1","media_key":"3_1982225220598464512","start":12,"url":"https://t.co/lrN2d4vauD"}]},"geo":{},"id":"1982225228789960905","lang":"zh","note_tweet":{"entities":{}},"possibly_sensitive":false,"public_metrics":{"bookmark_count":0,"impression_count":0,"like_count":0,"quote_count":0,"reply_count":0,"retweet_count":0},"reply_settings":"everyone","text":"连阴影都如思绪般杂乱. https://t.co/lrN2d4vauD"}],"users":[{"created_at":"2024-01-02T01:22:57.000Z","description":"猫，诗歌，精神动力学。艺术，朝闻道，波粒二象性。不断寻找着广播塔的星际候鸟。 | “我们彻夜飞旋，直至没入火焰。” | 匿名提问箱⬇️ | 🚪88/158","entities":{"url":{"urls":[{"display_url":"ngl.link/anincandescenc…","end":23,"expanded_url":"https://ngl.link/anincandescence1","start":0,"url":"https://t.co/iO6MRJNm9j"}]}},"id":"1741993395910811648","location":"天鹅座X-1","name":"炽烈已极","pinned_tweet_id":"1976277813784457417","profile_image_url":"https://pbs.twimg.com/profile_images/1967287311504465922/Z7d-hW5p_normal.jpg","protected":false,"public_metrics":{"followers_count":1251,"following_count":213,"like_count":10986,"listed_count":3,"media_count":829,"tweet_count":4198},"url":"https://t.co/iO6MRJNm9j","username":"AnIncandescence","verified":false}]}}