{"data":{"article":{},"attachments":{},"author_id":"1741993395910811648","conversation_id":"1986048091691041040","created_at":"2025-11-05T12:32:03.000Z","edit_controls":{"editable_until":"2025-11-05T13:32:03.000Z","edits_remaining":5,"is_edit_eligible":false},"edit_history_tweet_ids":["1986048865234014269"],"entities":{},"geo":{},"id":"1986048865234014269","in_reply_to_user_id":"1741993395910811648","lang":"zh","note_tweet":{"entities":{}},"possibly_sensitive":false,"public_metrics":{"bookmark_count":0,"impression_count":0,"like_count":0,"quote_count":0,"reply_count":0,"retweet_count":0},"referenced_tweets":[{"id":"1986048091691041040","type":"replied_to"}],"reply_settings":"everyone","text":"找个空教室躲起来哭，太好了，还有没人的教室啊"},"includes":{"media":[{"height":2048,"media_key":"3_1986048051648077824","public_metrics":{},"type":"photo","url":"https://pbs.twimg.com/media/G4_cLjFXIAAebQI.jpg","width":1536},{"height":1168,"media_key":"3_1986048051622907904","public_metrics":{},"type":"photo","url":"https://pbs.twimg.com/media/G4_cLi_XEAATQLG.jpg","width":2048},{"height":2048,"media_key":"3_1986048051668992000","public_metrics":{},"type":"photo","url":"https://pbs.twimg.com/media/G4_cLjKWQAAC_HC.jpg","width":1536}],"tweets":[{"article":{},"attachments":{},"author_id":"1741993395910811648","conversation_id":"1986048091691041040","created_at":"2025-11-05T12:32:03.000Z","edit_controls":{"editable_until":"2025-11-05T13:32:03.000Z","edits_remaining":5,"is_edit_eligible":false},"edit_history_tweet_ids":["1986048865234014269"],"entities":{},"geo":{},"id":"1986048865234014269","in_reply_to_user_id":"1741993395910811648","lang":"zh","note_tweet":{"entities":{}},"possibly_sensitive":false,"public_metrics":{"bookmark_count":0,"impression_count":0,"like_count":0,"quote_count":0,"reply_count":0,"retweet_count":0},"referenced_tweets":[{"id":"1986048091691041040","type":"replied_to"}],"reply_settings":"everyone","text":"找个空教室躲起来哭，太好了，还有没人的教室啊"},{"article":{},"attachments":{"media_keys":["3_1986048051648077824","3_1986048051622907904","3_1986048051668992000"]},"author_id":"1741993395910811648","conversation_id":"1986048091691041040","created_at":"2025-11-05T12:28:58.000Z","edit_controls":{"editable_until":"2025-11-05T13:28:58.000Z","edits_remaining":5,"is_edit_eligible":false},"edit_history_tweet_ids":["1986048091691041040"],"entities":{"urls":[{"display_url":"pic.x.com/McPgjLFSwP","end":120,"expanded_url":"https://x.com/AnIncandescence/status/1986048091691041040/photo/1","media_key":"3_1986048051648077824","start":97,"url":"https://t.co/McPgjLFSwP"},{"display_url":"pic.x.com/McPgjLFSwP","end":120,"expanded_url":"https://x.com/AnIncandescence/status/1986048091691041040/photo/1","media_key":"3_1986048051622907904","start":97,"url":"https://t.co/McPgjLFSwP"},{"display_url":"pic.x.com/McPgjLFSwP","end":120,"expanded_url":"https://x.com/AnIncandescence/status/1986048091691041040/photo/1","media_key":"3_1986048051668992000","start":97,"url":"https://t.co/McPgjLFSwP"}]},"geo":{},"id":"1986048091691041040","lang":"zh","note_tweet":{"entities":{}},"possibly_sensitive":false,"public_metrics":{"bookmark_count":0,"impression_count":6,"like_count":1,"quote_count":0,"reply_count":1,"retweet_count":0},"reply_settings":"everyone","text":"人们脸上都挂着笑容，就只有我在思考死亡的姿态如何是好。\n\n同一节课的或同个专业的哪怕是华人也无法融入，被世界孤立了一样。他们聊地好开心，如果我不出声就是完全的空气，然后笑着聊着走了留下我一个人 https://t.co/McPgjLFSwP"}],"users":[{"created_at":"2024-01-02T01:22:57.000Z","description":"猫，诗歌，精神动力学。艺术，朝闻道，波粒二象性。不断寻找着广播塔的星际候鸟。 | “我们彻夜飞旋，直至没入火焰。” | 匿名提问箱⬇️ | 🚪88/158","entities":{"url":{"urls":[{"display_url":"ngl.link/anincandescenc…","end":23,"expanded_url":"https://ngl.link/anincandescence1","start":0,"url":"https://t.co/iO6MRJNm9j"}]}},"id":"1741993395910811648","location":"天鹅座X-1","name":"炽烈已极","pinned_tweet_id":"1976277813784457417","profile_image_url":"https://pbs.twimg.com/profile_images/1967287311504465922/Z7d-hW5p_normal.jpg","protected":false,"public_metrics":{"followers_count":1258,"following_count":212,"like_count":11120,"listed_count":4,"media_count":836,"tweet_count":4265},"url":"https://t.co/iO6MRJNm9j","username":"AnIncandescence","verified":false}]}}