{"data":{"article":{},"attachments":{},"author_id":"1741993395910811648","conversation_id":"1944652805501030822","created_at":"2025-07-14T06:58:53.000Z","edit_controls":{"editable_until":"2025-07-14T07:58:53.000Z","edits_remaining":5,"is_edit_eligible":false},"edit_history_tweet_ids":["1944652805501030822"],"entities":{"mentions":[{"end":12,"id":"1481172876589821952","start":3,"username":"pyke2076"},{"end":67,"id":"1298038130063208449","start":52,"username":"yayadezahuopu_"}]},"geo":{},"id":"1944652805501030822","lang":"zh","note_tweet":{"entities":{}},"possibly_sensitive":false,"public_metrics":{"bookmark_count":0,"impression_count":0,"like_count":0,"quote_count":0,"reply_count":0,"retweet_count":7},"referenced_tweets":[{"id":"1944648230127735140","type":"retweeted"}],"reply_settings":"everyone","text":"RT @pyke2076: 5555fo 了，抽个有点抽象的奖（），哈哈哈哈，抽一个人送秒潮或者杯子，是@yayadezahuopu_ 家的，到时候由他家发货\n参与方式：转发+评论，这周四晚上 8 点开，然后再抽两个：KFCv 你 50\n（os： 这个不是推广啊啊啊啊） htt…"},"includes":{"media":[{"height":1192,"media_key":"3_1944648217645449216","public_metrics":{},"type":"photo","url":"https://pbs.twimg.com/media/GvzHQDHagAAFRN5.jpg","width":1170},{"height":800,"media_key":"3_1944648217808773120","public_metrics":{},"type":"photo","url":"https://pbs.twimg.com/media/GvzHQDuWoAA8d0S.jpg","width":800},{"height":800,"media_key":"3_1944648217662312448","public_metrics":{},"type":"photo","url":"https://pbs.twimg.com/media/GvzHQDLb0AA8SMA.jpg","width":800}],"tweets":[{"article":{},"attachments":{},"author_id":"1741993395910811648","conversation_id":"1944652805501030822","created_at":"2025-07-14T06:58:53.000Z","edit_controls":{"editable_until":"2025-07-14T07:58:53.000Z","edits_remaining":5,"is_edit_eligible":false},"edit_history_tweet_ids":["1944652805501030822"],"entities":{"mentions":[{"end":12,"id":"1481172876589821952","start":3,"username":"pyke2076"},{"end":67,"id":"1298038130063208449","start":52,"username":"yayadezahuopu_"}]},"geo":{},"id":"1944652805501030822","lang":"zh","note_tweet":{"entities":{}},"possibly_sensitive":false,"public_metrics":{"bookmark_count":0,"impression_count":0,"like_count":0,"quote_count":0,"reply_count":0,"retweet_count":7},"referenced_tweets":[{"id":"1944648230127735140","type":"retweeted"}],"reply_settings":"everyone","text":"RT @pyke2076: 5555fo 了，抽个有点抽象的奖（），哈哈哈哈，抽一个人送秒潮或者杯子，是@yayadezahuopu_ 家的，到时候由他家发货\n参与方式：转发+评论，这周四晚上 8 点开，然后再抽两个：KFCv 你 50\n（os： 这个不是推广啊啊啊啊） htt…"},{"article":{},"attachments":{"media_keys":["3_1944648217645449216","3_1944648217808773120","3_1944648217662312448"]},"author_id":"1481172876589821952","context_annotations":[{"domain":{"description":"Categories within Brand Verticals that narrow down the scope of Brands","id":"46","name":"Business Taxonomy"},"entity":{"description":"Brands, companies, advertisers and every non-person handle with the profit intent related to offline and online games such as gaming consoles, tabletop games, video game publishers","id":"1557696940178935808","name":"Gaming Business"}}],"conversation_id":"1944648230127735140","created_at":"2025-07-14T06:40:42.000Z","edit_controls":{"editable_until":"2025-07-14T07:40:42.000Z","edits_remaining":5,"is_edit_eligible":false},"edit_history_tweet_ids":["1944648230127735140"],"entities":{"mentions":[{"end":53,"id":"1298038130063208449","start":38,"username":"yayadezahuopu_"}],"urls":[{"display_url":"pic.x.com/Ye5MsjI5TJ","end":145,"expanded_url":"https://x.com/pyke2076/status/1944648230127735140/photo/1","media_key":"3_1944648217645449216","start":122,"url":"https://t.co/Ye5MsjI5TJ"},{"display_url":"pic.x.com/Ye5MsjI5TJ","end":145,"expanded_url":"https://x.com/pyke2076/status/1944648230127735140/photo/1","media_key":"3_1944648217808773120","start":122,"url":"https://t.co/Ye5MsjI5TJ"},{"display_url":"pic.x.com/Ye5MsjI5TJ","end":145,"expanded_url":"https://x.com/pyke2076/status/1944648230127735140/photo/1","media_key":"3_1944648217662312448","start":122,"url":"https://t.co/Ye5MsjI5TJ"}]},"geo":{},"id":"1944648230127735140","lang":"zh","note_tweet":{"entities":{}},"possibly_sensitive":false,"public_metrics":{"bookmark_count":0,"impression_count":150,"like_count":13,"quote_count":0,"reply_count":9,"retweet_count":7},"reply_settings":"everyone","text":"5555fo 了，抽个有点抽象的奖（），哈哈哈哈，抽一个人送秒潮或者杯子，是@yayadezahuopu_ 家的，到时候由他家发货\n参与方式：转发+评论，这周四晚上 8 点开，然后再抽两个：KFCv 你 50\n（os： 这个不是推广啊啊啊啊） https://t.co/Ye5MsjI5TJ"}],"users":[{"created_at":"2024-01-02T01:22:57.000Z","description":"猫，诗歌，精神动力学。艺术，C#，波粒二象性。不断寻找着广播塔的星际候鸟。 | “我们彻夜飞旋，直至没入火焰。” | 匿名提问箱⬇️ | 🚪88/158 | 不卖东西","entities":{"url":{"urls":[{"display_url":"ngl.link/anincandescence","end":23,"expanded_url":"https://ngl.link/anincandescence","start":0,"url":"https://t.co/MuEKSg4tIS"}]}},"id":"1741993395910811648","location":"天鹅座X-1","name":"炽烈已极","pinned_tweet_id":"1926637878257311824","profile_image_url":"https://pbs.twimg.com/profile_images/1930288376399155200/A42NAeD9_normal.jpg","protected":false,"public_metrics":{"followers_count":1049,"following_count":204,"like_count":9008,"listed_count":1,"media_count":659,"tweet_count":3227},"url":"https://t.co/MuEKSg4tIS","username":"AnIncandescence","verified":false},{"created_at":"2022-01-12T07:55:43.000Z","description":"当你离去之后，你仍在我的视线里。","id":"1481172876589821952","name":"bunny","profile_image_url":"https://pbs.twimg.com/profile_images/1739460199323435008/cSDInbKL_normal.jpg","protected":false,"public_metrics":{"followers_count":5567,"following_count":1169,"like_count":58487,"listed_count":7,"media_count":2671,"tweet_count":15471},"username":"pyke2076","verified":false},{"created_at":"2020-08-24T23:23:11.000Z","description":"小玩具淘宝店：鸭鸭的杂货铺，可以发全球🌍，需要微信购买，需要玩具推荐请私信，找客服说推特来的给大家优惠！！！有比我便宜，我就改价格，请直接私信我","entities":{"url":{"urls":[{"display_url":"m.tb.cn/h.UuRchai","end":23,"expanded_url":"https://m.tb.cn/h.UuRchai","start":0,"url":"https://t.co/Ts2WoiOdwJ"}]}},"id":"1298038130063208449","location":"一爱情侣，玩具由女朋友测评，说性骚扰请举证","name":"🍑：鸭鸭的杂货铺（送对象，送优惠）","pinned_tweet_id":"1944407820423639312","profile_image_url":"https://pbs.twimg.com/profile_images/1800053920905244672/fWXFshAL_normal.jpg","protected":false,"public_metrics":{"followers_count":27592,"following_count":1081,"like_count":84726,"listed_count":32,"media_count":1128,"tweet_count":38223},"url":"https://t.co/Ts2WoiOdwJ","username":"yayadezahuopu_","verified":true}]}}