{"data":{"article":{},"attachments":{},"author_id":"1741993395910811648","conversation_id":"1904822735060287989","created_at":"2025-03-29T13:16:38.000Z","edit_controls":{"editable_until":"2025-03-29T14:16:38.000Z","edits_remaining":5,"is_edit_eligible":false},"edit_history_tweet_ids":["1905972369350590545"],"entities":{"mentions":[{"end":10,"id":"1597257668313260033","start":0,"username":"Minokakay"},{"end":24,"id":"1279702935102865409","start":11,"username":"YoselinZhang"}]},"geo":{},"id":"1905972369350590545","in_reply_to_user_id":"1597257668313260033","lang":"zh","note_tweet":{"entities":{}},"possibly_sensitive":false,"public_metrics":{"bookmark_count":0,"impression_count":0,"like_count":0,"quote_count":0,"reply_count":0,"retweet_count":0},"referenced_tweets":[{"id":"1905970340351926714","type":"replied_to"}],"reply_settings":"everyone","text":"@Minokakay @YoselinZhang 来找我买😋"},"includes":{"tweets":[{"article":{},"attachments":{},"author_id":"1741993395910811648","conversation_id":"1904822735060287989","created_at":"2025-03-29T13:16:38.000Z","edit_controls":{"editable_until":"2025-03-29T14:16:38.000Z","edits_remaining":5,"is_edit_eligible":false},"edit_history_tweet_ids":["1905972369350590545"],"entities":{"mentions":[{"end":10,"id":"1597257668313260033","start":0,"username":"Minokakay"},{"end":24,"id":"1279702935102865409","start":11,"username":"YoselinZhang"}]},"geo":{},"id":"1905972369350590545","in_reply_to_user_id":"1597257668313260033","lang":"zh","note_tweet":{"entities":{}},"possibly_sensitive":false,"public_metrics":{"bookmark_count":0,"impression_count":0,"like_count":0,"quote_count":0,"reply_count":0,"retweet_count":0},"referenced_tweets":[{"id":"1905970340351926714","type":"replied_to"}],"reply_settings":"everyone","text":"@Minokakay @YoselinZhang 来找我买😋"},{"article":{},"attachments":{},"author_id":"1597257668313260033","conversation_id":"1904822735060287989","created_at":"2025-03-29T13:08:35.000Z","edit_controls":{"editable_until":"2025-03-29T14:08:35.000Z","edits_remaining":5,"is_edit_eligible":false},"edit_history_tweet_ids":["1905970340351926714"],"entities":{"mentions":[{"end":16,"id":"1741993395910811648","start":0,"username":"AnIncandescence"},{"end":30,"id":"1279702935102865409","start":17,"username":"YoselinZhang"}]},"geo":{},"id":"1905970340351926714","in_reply_to_user_id":"1741993395910811648","lang":"ja","note_tweet":{"entities":{}},"possibly_sensitive":false,"public_metrics":{"bookmark_count":0,"impression_count":4,"like_count":1,"quote_count":0,"reply_count":1,"retweet_count":0},"referenced_tweets":[{"id":"1904836850113798161","type":"replied_to"}],"reply_settings":"everyone","text":"@AnIncandescence @YoselinZhang 想要"}],"users":[{"created_at":"2024-01-02T01:22:57.000Z","description":"互fo欢迎！ 猫，诗歌，精神动力学。艺术，C#，波粒二象性。回归曲线上的量子生物，无攻击性。 | “我们彻夜飞旋，直至没入火焰。” | 阴暗碎碎念纯享版@TauCeti_10700 | 🚪88/158 |  提问箱👇","entities":{"description":{"mentions":[{"end":90,"start":76,"username":"TauCeti_10700"}]},"url":{"urls":[{"display_url":"ngl.link/anincandescence","end":23,"expanded_url":"https://ngl.link/anincandescence","start":0,"url":"https://t.co/MuEKSg3VTk"}]}},"id":"1741993395910811648","location":"0°00′N 260°00′E Mars","name":"炽烈已极","pinned_tweet_id":"1905895186867400960","profile_image_url":"https://pbs.twimg.com/profile_images/1789433740277567488/d3KhwUX1_normal.jpg","protected":false,"public_metrics":{"followers_count":424,"following_count":181,"like_count":5541,"listed_count":1,"media_count":457,"tweet_count":2003},"url":"https://t.co/MuEKSg3VTk","username":"AnIncandescence","verified":false},{"created_at":"2022-11-28T15:54:46.000Z","description":"悲しくなるならそれでもいいなら，\nずっと一人で笑えよ。成渝半休学陰暗比高三生 阿斯ADHD Pansexual INFP MtX🇺🇦🏳️‍⚧️🏳️‍🌈TG https://t.co/jLmgEIa7Rt","entities":{"description":{"urls":[{"display_url":"t.me/minokakay","end":101,"expanded_url":"http://t.me/minokakay","start":78,"url":"https://t.co/jLmgEIa7Rt"}]}},"id":"1597257668313260033","location":"重庆市精神卫生中心门诊5楼","name":"Minokakay（日雌泰补色诺","pinned_tweet_id":"1899298005330899355","profile_image_url":"https://pbs.twimg.com/profile_images/1789594344930099200/wrFOWSe3_normal.jpg","protected":false,"public_metrics":{"followers_count":6127,"following_count":851,"like_count":39507,"listed_count":28,"media_count":704,"tweet_count":15565},"username":"Minokakay","verified":true},{"created_at":"2020-07-05T09:05:40.000Z","description":"07, ISFP, planning 26fall US, cisgender female & trans friendly, 中文&ENG","entities":{"url":{"urls":[{"display_url":"t.me/upsetallday","end":23,"expanded_url":"https://t.me/upsetallday","start":0,"url":"https://t.co/DrDwjEvGaG"}]}},"id":"1279702935102865409","location":"Self-destroy leads to rebirth ","name":"Yoselin💊🩸☠️","pinned_tweet_id":"1859296461709586614","profile_image_url":"https://pbs.twimg.com/profile_images/1858351609325162496/IJY_umTx_normal.jpg","protected":false,"public_metrics":{"followers_count":132,"following_count":193,"like_count":5219,"listed_count":0,"media_count":56,"tweet_count":1116},"url":"https://t.co/DrDwjEvGaG","username":"YoselinZhang","verified":false}]}}