{"data":{"article":{},"attachments":{},"author_id":"1741993395910811648","conversation_id":"2022498660303671662","created_at":"2026-02-14T12:01:25.000Z","edit_controls":{"editable_until":"2026-02-14T13:01:25.000Z","edits_remaining":5,"is_edit_eligible":false},"edit_history_tweet_ids":["2022642330818515315"],"entities":{"mentions":[{"end":15,"id":"1849043039496617984","start":0,"username":"Rinko_zero8964"}]},"geo":{},"id":"2022642330818515315","in_reply_to_user_id":"1849043039496617984","lang":"ja","note_tweet":{"entities":{}},"possibly_sensitive":false,"public_metrics":{"bookmark_count":0,"impression_count":0,"like_count":0,"quote_count":0,"reply_count":0,"retweet_count":0},"referenced_tweets":[{"id":"2022498660303671662","type":"replied_to"}],"reply_settings":"everyone","text":"@Rinko_zero8964 g向好啊（）"},"includes":{"tweets":[{"article":{},"attachments":{},"author_id":"1741993395910811648","conversation_id":"2022498660303671662","created_at":"2026-02-14T12:01:25.000Z","edit_controls":{"editable_until":"2026-02-14T13:01:25.000Z","edits_remaining":5,"is_edit_eligible":false},"edit_history_tweet_ids":["2022642330818515315"],"entities":{"mentions":[{"end":15,"id":"1849043039496617984","start":0,"username":"Rinko_zero8964"}]},"geo":{},"id":"2022642330818515315","in_reply_to_user_id":"1849043039496617984","lang":"ja","note_tweet":{"entities":{}},"possibly_sensitive":false,"public_metrics":{"bookmark_count":0,"impression_count":0,"like_count":0,"quote_count":0,"reply_count":0,"retweet_count":0},"referenced_tweets":[{"id":"2022498660303671662","type":"replied_to"}],"reply_settings":"everyone","text":"@Rinko_zero8964 g向好啊（）"},{"article":{},"attachments":{},"author_id":"1849043039496617984","conversation_id":"2022498660303671662","created_at":"2026-02-14T02:30:31.000Z","edit_controls":{"editable_until":"2026-02-14T03:30:31.000Z","edits_remaining":5,"is_edit_eligible":true},"edit_history_tweet_ids":["2022498660303671662"],"entities":{"urls":[{"display_url":"x.com/rinko_zero8964…","end":91,"expanded_url":"https://twitter.com/rinko_zero8964/status/2022481370325618806","start":68,"url":"https://t.co/wFvqIfqGdc"}]},"geo":{},"id":"2022498660303671662","lang":"zh","note_tweet":{"entities":{}},"possibly_sensitive":false,"public_metrics":{"bookmark_count":0,"impression_count":316,"like_count":21,"quote_count":0,"reply_count":8,"retweet_count":0},"referenced_tweets":[{"id":"2022481370325618806","type":"quoted"}],"reply_settings":"everyone","text":"草\n说个东西证明一下吧 我核吧十级\n真的严重恋血癖 以前看本子没猎奇血腥不看 因为一点想法都没有 就喜欢血腥 会很爽（（各种意义上的爽 https://t.co/wFvqIfqGdc"}],"users":[{"created_at":"2024-01-02T01:22:57.000Z","description":"猫，诗歌，精神动力学。艺术，朝闻道，波粒二象性。不断寻找着广播塔的星际候鸟。 | “我们彻夜飞旋，直至没入火焰。” | 匿名提问箱⬇️ | @TauCeti_10700 日常和碎碎念 | 🚪88/158","entities":{"description":{"mentions":[{"end":84,"start":70,"username":"TauCeti_10700"}]},"url":{"urls":[{"display_url":"ngl.link/anincandescenc…","end":23,"expanded_url":"https://ngl.link/anincandescence1","start":0,"url":"https://t.co/iO6MRJNTYR"}]}},"id":"1741993395910811648","location":"天鹅座X-1","name":"炽烈已极","pinned_tweet_id":"2010452086539145687","profile_image_url":"https://pbs.twimg.com/profile_images/2006317223414255617/jGT_GZyG_normal.jpg","protected":false,"public_metrics":{"followers_count":1690,"following_count":233,"like_count":13781,"listed_count":5,"media_count":1037,"tweet_count":5634},"url":"https://t.co/iO6MRJNTYR","username":"AnIncandescence","verified":false},{"created_at":"2024-10-23T10:59:58.000Z","description":"我思即我在｜我是林子｜如果没有回关请私信提醒我！｜我不吸毒！！！｜性别为无、｜輪郭の定まらない位置にいた人@Psych_Angel_","entities":{"description":{"mentions":[{"end":66,"start":53,"username":"Psych_Angel_"}]},"url":{"urls":[{"display_url":"t.me/Rinko_zero","end":23,"expanded_url":"http://t.me/Rinko_zero","start":0,"url":"https://t.co/rCvc9RNh89"}]}},"id":"1849043039496617984","location":"宛平南路600号","name":"Rinko","pinned_tweet_id":"2008491763561099436","profile_image_url":"https://pbs.twimg.com/profile_images/2004661650092359680/DqSlreCz_normal.jpg","protected":false,"public_metrics":{"followers_count":570,"following_count":528,"like_count":14427,"listed_count":1,"media_count":146,"tweet_count":7328},"url":"https://t.co/rCvc9RNh89","username":"Rinko_zero8964","verified":false}]}}