{"data":{"article":{},"attachments":{},"author_id":"1741993395910811648","conversation_id":"2025253187956211999","created_at":"2026-02-21T17:41:49.000Z","edit_controls":{"editable_until":"2026-02-21T18:41:49.000Z","edits_remaining":5,"is_edit_eligible":false},"edit_history_tweet_ids":["2025264710946578583"],"entities":{"mentions":[{"end":11,"id":"1558547901164318728","start":0,"username":"saiyadayoo"}],"urls":[{"description":"夢と現の狭間で青に溺れる。","display_url":"x.com/0__11xx?s=21","end":99,"expanded_url":"https://x.com/0__11xx?s=21","images":[{"height":200,"url":"https://pbs.twimg.com/news_img/1982806908537909248/7UcPuV8-?format=jpg&name=orig","width":200},{"height":150,"url":"https://pbs.twimg.com/news_img/1982806908537909248/7UcPuV8-?format=jpg&name=150x150","width":150}],"start":76,"status":200,"title":"夢鬱つ (@0__11Xx) on X","unwound_url":"https://x.com/0__11xx?s=21","url":"https://t.co/CedXpz1y6M"}]},"geo":{},"id":"2025264710946578583","in_reply_to_user_id":"1558547901164318728","lang":"zh","note_tweet":{"entities":{}},"possibly_sensitive":false,"public_metrics":{"bookmark_count":0,"impression_count":0,"like_count":0,"quote_count":0,"reply_count":0,"retweet_count":0},"referenced_tweets":[{"id":"2025259497665757432","type":"replied_to"}],"reply_settings":"everyone","text":"@saiyadayoo 20.讨厌的人，这个好像答过，那我再说几种类型hh 傲慢的，缺少同理心的，喜欢攀比的\n82.喜欢的画手，我推小夜呀！（）www\nhttps://t.co/CedXpz1y6M\n喜欢这个！"},"includes":{"tweets":[{"article":{},"attachments":{},"author_id":"1741993395910811648","conversation_id":"2025253187956211999","created_at":"2026-02-21T17:41:49.000Z","edit_controls":{"editable_until":"2026-02-21T18:41:49.000Z","edits_remaining":5,"is_edit_eligible":false},"edit_history_tweet_ids":["2025264710946578583"],"entities":{"mentions":[{"end":11,"id":"1558547901164318728","start":0,"username":"saiyadayoo"}],"urls":[{"description":"夢と現の狭間で青に溺れる。","display_url":"x.com/0__11xx?s=21","end":99,"expanded_url":"https://x.com/0__11xx?s=21","images":[{"height":200,"url":"https://pbs.twimg.com/news_img/1982806908537909248/7UcPuV8-?format=jpg&name=orig","width":200},{"height":150,"url":"https://pbs.twimg.com/news_img/1982806908537909248/7UcPuV8-?format=jpg&name=150x150","width":150}],"start":76,"status":200,"title":"夢鬱つ (@0__11Xx) on X","unwound_url":"https://x.com/0__11xx?s=21","url":"https://t.co/CedXpz1y6M"}]},"geo":{},"id":"2025264710946578583","in_reply_to_user_id":"1558547901164318728","lang":"zh","note_tweet":{"entities":{}},"possibly_sensitive":false,"public_metrics":{"bookmark_count":0,"impression_count":0,"like_count":0,"quote_count":0,"reply_count":0,"retweet_count":0},"referenced_tweets":[{"id":"2025259497665757432","type":"replied_to"}],"reply_settings":"everyone","text":"@saiyadayoo 20.讨厌的人，这个好像答过，那我再说几种类型hh 傲慢的，缺少同理心的，喜欢攀比的\n82.喜欢的画手，我推小夜呀！（）www\nhttps://t.co/CedXpz1y6M\n喜欢这个！"},{"article":{},"attachments":{},"author_id":"1558547901164318728","conversation_id":"2025253187956211999","created_at":"2026-02-21T17:21:06.000Z","edit_controls":{"editable_until":"2026-02-21T18:21:06.000Z","edits_remaining":5,"is_edit_eligible":false},"edit_history_tweet_ids":["2025259497665757432"],"entities":{"mentions":[{"end":16,"id":"1741993395910811648","start":0,"username":"AnIncandescence"}]},"geo":{},"id":"2025259497665757432","in_reply_to_user_id":"1741993395910811648","lang":"und","note_tweet":{"entities":{}},"possibly_sensitive":false,"public_metrics":{"bookmark_count":0,"impression_count":11,"like_count":1,"quote_count":0,"reply_count":1,"retweet_count":0},"referenced_tweets":[{"id":"2025253187956211999","type":"replied_to"}],"reply_settings":"everyone","text":"@AnIncandescence 20、82！"}],"users":[{"created_at":"2024-01-02T01:22:57.000Z","description":"猫，诗歌，精神动力学。艺术，朝闻道，波粒二象性。不断寻找着广播塔的星际候鸟。 | “我们彻夜飞旋，直至没入火焰。” | 倒影@TauCeti_10700 计划这个号机的浓度更高一些 | 🚪88/158","entities":{"description":{"mentions":[{"end":76,"start":62,"username":"TauCeti_10700"}]},"url":{"urls":[{"display_url":"ngl.link/anincandescenc…","end":23,"expanded_url":"https://ngl.link/anincandescence1","start":0,"url":"https://t.co/iO6MRJNTYR"}]}},"id":"1741993395910811648","location":"天鹅座X-1 //⬇️ 匿名提问箱","name":"炽烈已极","pinned_tweet_id":"2024076888923365667","profile_image_url":"https://pbs.twimg.com/profile_images/2006317223414255617/jGT_GZyG_normal.jpg","protected":false,"public_metrics":{"followers_count":1724,"following_count":234,"like_count":14192,"listed_count":5,"media_count":1061,"tweet_count":5867},"url":"https://t.co/iO6MRJNTYR","username":"AnIncandescence","verified":false},{"created_at":"2022-08-13T20:16:01.000Z","description":"連你也不要我了嗎","id":"1558547901164318728","location":"天堂","name":"ʚ✞ɞ","pinned_tweet_id":"2000234744479678542","profile_image_url":"https://pbs.twimg.com/profile_images/1873311243852976128/T-qCTONh_normal.jpg","protected":false,"public_metrics":{"followers_count":191,"following_count":381,"like_count":21209,"listed_count":0,"media_count":444,"tweet_count":10422},"username":"saiyadayoo","verified":false}]}}